{"stats":{"minecraft:picked_up":{"minecraft:iron_nugget":1,"minecraft:gold_nugget":1},"minecraft:used":{"minecraft:damaged_anvil":1,"minecraft:iron_sword":3},"minecraft:custom":{"minecraft:jump":8,"minecraft:time_since_rest":2200,"minecraft:damage_dealt":520,"minecraft:leave_game":1,"minecraft:sprint_one_cm":444,"minecraft:play_time":2200,"minecraft:time_since_death":2200,"minecraft:walk_one_cm":2097,"minecraft:total_world_time":2290,"minecraft:mob_kills":3,"minecraft:interact_with_anvil":2,"minecraft:fly_one_cm":267},"minecraft:killed":{"minecraft:skeleton":2,"minecraft:zombie":1}},"DataVersion":3465}