{"stats":{"minecraft:custom":{"minecraft:jump":4,"minecraft:time_since_rest":1953,"minecraft:damage_dealt":3200,"minecraft:leave_game":1,"minecraft:play_time":1953,"minecraft:walk_one_cm":6025,"minecraft:time_since_death":1953,"minecraft:total_world_time":1965,"minecraft:mob_kills":18,"minecraft:drop":1},"minecraft:dropped":{"minecraft:potato":1},"minecraft:killed":{"minecraft:villager":1,"minecraft:zombie":17},"minecraft:picked_up":{"minecraft:iron_nugget":19,"minecraft:gold_nugget":8,"minecraft:potato":1}},"DataVersion":3465}